odoo/addons/web_notify_channel_message/README.rst
odoo/addons/web_notify_channel_message/__init__.py
odoo/addons/web_notify_channel_message/__manifest__.py
odoo/addons/web_notify_channel_message/i18n/fr.po
odoo/addons/web_notify_channel_message/i18n/it.po
odoo/addons/web_notify_channel_message/i18n/web_notify_channel_message.pot
odoo/addons/web_notify_channel_message/models/__init__.py
odoo/addons/web_notify_channel_message/models/mail_channel.py
odoo/addons/web_notify_channel_message/readme/CONTRIBUTORS.rst
odoo/addons/web_notify_channel_message/readme/DESCRIPTION.rst
odoo/addons/web_notify_channel_message/static/description/icon.png
odoo/addons/web_notify_channel_message/static/description/index.html
odoo14_addon_web_notify_channel_message-14.0.1.0.1.dev8.dist-info/METADATA
odoo14_addon_web_notify_channel_message-14.0.1.0.1.dev8.dist-info/WHEEL
odoo14_addon_web_notify_channel_message-14.0.1.0.1.dev8.dist-info/top_level.txt
odoo14_addon_web_notify_channel_message-14.0.1.0.1.dev8.dist-info/RECORD
