Metadata-Version: 2.1
Name: odoo14-addon-web_notify_channel_message
Version: 14.0.1.0.1.dev8
Summary: Send an instant notification to channel users when a new message is posted
Home-page: https://github.com/OCA/web
Author: ForgeFlow, Odoo Community Association (OCA)
Author-email: support@odoo-community.org
License: AGPL-3
Classifier: Programming Language :: Python
Classifier: Framework :: Odoo
Classifier: Framework :: Odoo :: 14.0
Classifier: License :: OSI Approved :: GNU Affero General Public License v3
Classifier: Development Status :: 3 - Alpha
Requires-Python: >=3.6
Requires-Dist: odoo14-addon-web-notify
Requires-Dist: odoo<14.1dev,>=14.0a
